{
	"format_version": "1.8.0",
	"animations": {
		"animation.salaberrant.ground_idle": {
			"loop": true,
			"animation_length": 3,
			"bones": {
				"torso": {
					"rotation": {
						"0.0": [55, 0, 0],
						"0.75": {
							"pre": [57.5, 0, 0],
							"post": [57.5, 0, 0],
							"lerp_mode": "catmullrom"
						},
						"1.5": [55, 0, 0],
						"2.25": {
							"pre": [57.5, 0, 0],
							"post": [57.5, 0, 0],
							"lerp_mode": "catmullrom"
						},
						"3.0": [55, 0, 0]
					},
					"position": {
						"0.0": [0, 0, 0],
						"0.75": {
							"pre": [0, -0.25, 0],
							"post": [0, -0.25, 0],
							"lerp_mode": "catmullrom"
						},
						"1.5": [0, 0, 0],
						"2.25": {
							"pre": [0, -0.25, 0],
							"post": [0, -0.25, 0],
							"lerp_mode": "catmullrom"
						},
						"3.0": [0, 0, 0]
					}
				},
				"waist": {
					"rotation": {
						"0.0": [-30, 0, 0],
						"0.75": {
							"pre": [-27.5, 0, 0],
							"post": [-27.5, 0, 0],
							"lerp_mode": "catmullrom"
						},
						"1.5": [-30, 0, 0],
						"2.25": {
							"pre": [-27.5, 0, 0],
							"post": [-27.5, 0, 0],
							"lerp_mode": "catmullrom"
						},
						"3.0": [-30, 0, 0]
					}
				},
				"chest": {
					"rotation": {
						"0.0": [22.5, 0, 0],
						"0.75": {
							"pre": [17.5, 0, 0],
							"post": [17.5, 0, 0],
							"lerp_mode": "catmullrom"
						},
						"1.5": [22.5, 0, 0],
						"2.25": {
							"pre": [17.5, 0, 0],
							"post": [17.5, 0, 0],
							"lerp_mode": "catmullrom"
						},
						"3.0": [22.5, 0, 0]
					}
				},
				"neck": {
					"rotation": {
						"0.0": [22.5, 0, 0],
						"0.75": {
							"pre": [32.5, 0, 0],
							"post": [32.5, 0, 0],
							"lerp_mode": "catmullrom"
						},
						"1.5": [22.5, 0, 0],
						"2.25": {
							"pre": [32.5, 0, 0],
							"post": [32.5, 0, 0],
							"lerp_mode": "catmullrom"
						},
						"3.0": [22.5, 0, 0]
					}
				},
				"neck2": {
					"rotation": {
						"0.0": [22.5, 0, 0],
						"0.75": {
							"pre": [12.5, 0, 0],
							"post": [12.5, 0, 0],
							"lerp_mode": "catmullrom"
						},
						"1.5": [22.5, 0, 0],
						"2.25": {
							"pre": [12.5, 0, 0],
							"post": [12.5, 0, 0],
							"lerp_mode": "catmullrom"
						},
						"3.0": [22.5, 0, 0]
					}
				},
				"head": {
					"rotation": {
						"0.0": [-87.5, 0, 0],
						"0.75": {
							"pre": [-87.5, 0, 0],
							"post": [-87.5, 0, 0],
							"lerp_mode": "catmullrom"
						},
						"1.5": [-87.5, 0, 0],
						"2.25": {
							"pre": [-87.5, 0, 0],
							"post": [-87.5, 0, 0],
							"lerp_mode": "catmullrom"
						},
						"3.0": [-87.5, 0, 0]
					}
				},
				"jaw": {
					"rotation": {
						"0.0": [27.5, 0, 0],
						"0.75": {
							"pre": [32.5, 0, 0],
							"post": [32.5, 0, 0],
							"lerp_mode": "catmullrom"
						},
						"1.5": [27.5, 0, 0],
						"2.25": {
							"pre": [32.5, 0, 0],
							"post": [32.5, 0, 0],
							"lerp_mode": "catmullrom"
						},
						"3.0": [27.5, 0, 0]
					}
				},
				"tongue": {
					"rotation": {
						"0.0": [2.43938, -12.48791, 0.55404],
						"1.5": [2.43938, -12.48791, 0.55404],
						"3.0": [2.43938, -12.48791, 0.55404]
					}
				},
				"tongue2": {
					"rotation": {
						"0.0": [17.5, -22.5, 0],
						"1.5": [17.5, -22.5, 0],
						"3.0": [17.5, -22.5, 0]
					}
				},
				"tongue3": {
					"rotation": {
						"0.0": [17.5, 0, 0],
						"1.5": [17.5, 0, 0],
						"3.0": [17.5, 0, 0]
					}
				},
				"leg_right": {
					"rotation": {
						"0.0": [44, -33, -48],
						"0.75": {
							"pre": [43.03304, -34.37725, -46.25694],
							"post": [43.03304, -34.37725, -46.25694],
							"lerp_mode": "catmullrom"
						},
						"1.5": [44, -33, -48],
						"2.25": {
							"pre": [43.03304, -34.37725, -46.25694],
							"post": [43.03304, -34.37725, -46.25694],
							"lerp_mode": "catmullrom"
						},
						"3.0": [44, -33, -48]
					},
					"position": {
						"0.0": [0, 0, 0],
						"0.75": {
							"pre": [0, -0.25, 0],
							"post": [0, -0.25, 0],
							"lerp_mode": "catmullrom"
						},
						"1.5": [0, 0, 0],
						"2.25": {
							"pre": [0, -0.25, 0],
							"post": [0, -0.25, 0],
							"lerp_mode": "catmullrom"
						},
						"3.0": [0, 0, 0]
					}
				},
				"leg_right2": {
					"rotation": {
						"0.0": [9, -4, -75],
						"0.75": {
							"pre": [9.19486, -3.52555, -77.96866],
							"post": [9.19486, -3.52555, -77.96866],
							"lerp_mode": "catmullrom"
						},
						"1.5": [9, -4, -75],
						"2.25": {
							"pre": [9.19486, -3.52555, -77.96866],
							"post": [9.19486, -3.52555, -77.96866],
							"lerp_mode": "catmullrom"
						},
						"3.0": [9, -4, -75]
					}
				},
				"foot_right": {
					"rotation": {
						"0.0": [-2, 0, -17],
						"0.75": {
							"pre": [-1.9997, 0.0349, -16.00061],
							"post": [-1.9997, 0.0349, -16.00061],
							"lerp_mode": "catmullrom"
						},
						"1.5": [-2, 0, -17],
						"2.25": {
							"pre": [-1.9997, 0.0349, -16.00061],
							"post": [-1.9997, 0.0349, -16.00061],
							"lerp_mode": "catmullrom"
						},
						"3.0": [-2, 0, -17]
					}
				},
				"toe_right2": {
					"rotation": {
						"0.0": [0, 0, 20],
						"1.5": [0, 0, 20],
						"3.0": [0, 0, 20]
					}
				},
				"toe_right2_2": {
					"rotation": {
						"0.0": [-0.7667, -7.45455, 15.05947],
						"1.5": [-0.7667, -7.45455, 15.05947],
						"3.0": [-0.7667, -7.45455, 15.05947]
					}
				},
				"toe_right3": {
					"rotation": {
						"0.0": [0, 0, 20],
						"1.5": [0, 0, 20],
						"3.0": [0, 0, 20]
					}
				},
				"toe_right3_2": {
					"rotation": {
						"0.0": [0, 0, 20],
						"1.5": [0, 0, 20],
						"3.0": [0, 0, 20]
					}
				},
				"toe_right1_rotation": {
					"rotation": {
						"0.0": [-10, 0, 0],
						"1.5": [-10, 0, 0],
						"3.0": [-10, 0, 0]
					}
				},
				"toe_right1_2": {
					"rotation": {
						"0.0": [-0.82283, -19.93902, 20.20413],
						"1.5": [-0.82283, -19.93902, 20.20413],
						"3.0": [-0.82283, -19.93902, 20.20413]
					}
				},
				"toe_right4_rotation": {
					"rotation": {
						"0.0": [-0.32652, 2.4786, 9.99294],
						"1.5": [-0.32652, 2.4786, 9.99294],
						"3.0": [-0.32652, 2.4786, 9.99294]
					}
				},
				"toe_right4_2": {
					"rotation": {
						"0.0": [2.20421, 12.25878, 20.28417],
						"1.5": [2.20421, 12.25878, 20.28417],
						"3.0": [2.20421, 12.25878, 20.28417]
					}
				},
				"toe_right5_rotation": {
					"rotation": {
						"0.0": [-22.49067, 0.43399, -20.03793],
						"1.5": [-22.49067, 0.43399, -20.03793],
						"3.0": [-22.49067, 0.43399, -20.03793]
					}
				},
				"toe_right5_2": {
					"rotation": {
						"0.0": [1.20002, 26.16179, 25.98387],
						"1.5": [1.20002, 26.16179, 25.98387],
						"3.0": [1.20002, 26.16179, 25.98387]
					}
				},
				"leg_left": {
					"rotation": {
						"0.0": [44, 33, 48],
						"0.75": {
							"pre": [43.03304, 34.37725, 46.25694],
							"post": [43.03304, 34.37725, 46.25694],
							"lerp_mode": "catmullrom"
						},
						"1.5": [44, 33, 48],
						"2.25": {
							"pre": [43.03304, 34.37725, 46.25694],
							"post": [43.03304, 34.37725, 46.25694],
							"lerp_mode": "catmullrom"
						},
						"3.0": [44, 33, 48]
					},
					"position": {
						"0.0": [0, 0, 0],
						"0.75": {
							"pre": [0, -0.25, 0],
							"post": [0, -0.25, 0],
							"lerp_mode": "catmullrom"
						},
						"1.5": [0, 0, 0],
						"2.25": {
							"pre": [0, -0.25, 0],
							"post": [0, -0.25, 0],
							"lerp_mode": "catmullrom"
						},
						"3.0": [0, 0, 0]
					}
				},
				"leg_left2": {
					"rotation": {
						"0.0": [9, 4, 75],
						"0.75": {
							"pre": [9.19486, 3.52555, 77.96866],
							"post": [9.19486, 3.52555, 77.96866],
							"lerp_mode": "catmullrom"
						},
						"1.5": [9, 4, 75],
						"2.25": {
							"pre": [9.19486, 3.52555, 77.96866],
							"post": [9.19486, 3.52555, 77.96866],
							"lerp_mode": "catmullrom"
						},
						"3.0": [9, 4, 75]
					}
				},
				"foot_left": {
					"rotation": {
						"0.0": [-2, 0, 17],
						"0.75": {
							"pre": [-1.9997, -0.0349, 16.00061],
							"post": [-1.9997, -0.0349, 16.00061],
							"lerp_mode": "catmullrom"
						},
						"1.5": [-2, 0, 17],
						"2.25": {
							"pre": [-1.9997, -0.0349, 16.00061],
							"post": [-1.9997, -0.0349, 16.00061],
							"lerp_mode": "catmullrom"
						},
						"3.0": [-2, 0, 17]
					}
				},
				"toe_left1_rotation": {
					"rotation": {
						"0.0": [-10, 0, 0],
						"1.5": [-10, 0, 0],
						"3.0": [-10, 0, 0]
					}
				},
				"toe_left1_2": {
					"rotation": {
						"0.0": [-0.82283, 19.93902, -20.20413],
						"1.5": [-0.82283, 19.93902, -20.20413],
						"3.0": [-0.82283, 19.93902, -20.20413]
					}
				},
				"toe_left2": {
					"rotation": {
						"0.0": [0, 0, -20],
						"1.5": [0, 0, -20],
						"3.0": [0, 0, -20]
					}
				},
				"toe_left2_2": {
					"rotation": {
						"0.0": [-0.7667, 7.45455, -15.05947],
						"1.5": [-0.7667, 7.45455, -15.05947],
						"3.0": [-0.7667, 7.45455, -15.05947]
					}
				},
				"toe_left3": {
					"rotation": {
						"0.0": [0, 0, -20],
						"1.5": [0, 0, -20],
						"3.0": [0, 0, -20]
					}
				},
				"toe_left3_2": {
					"rotation": {
						"0.0": [0, 0, -20],
						"1.5": [0, 0, -20],
						"3.0": [0, 0, -20]
					}
				},
				"toe_left4_rotation": {
					"rotation": {
						"0.0": [-0.32652, -2.4786, -9.99294],
						"1.5": [-0.32652, -2.4786, -9.99294],
						"3.0": [-0.32652, -2.4786, -9.99294]
					}
				},
				"toe_left4_2": {
					"rotation": {
						"0.0": [2.20421, -12.25878, -20.28417],
						"1.5": [2.20421, -12.25878, -20.28417],
						"3.0": [2.20421, -12.25878, -20.28417]
					}
				},
				"toe_left5_rotation": {
					"rotation": {
						"0.0": [-22.49067, -0.43399, 20.03793],
						"1.5": [-22.49067, -0.43399, 20.03793],
						"3.0": [-22.49067, -0.43399, 20.03793]
					}
				},
				"toe_left5_2": {
					"rotation": {
						"0.0": [1.20002, -26.16179, -25.98387],
						"1.5": [1.20002, -26.16179, -25.98387],
						"3.0": [1.20002, -26.16179, -25.98387]
					}
				},
				"arm_right": {
					"rotation": {
						"0.0": [-1, -56, -22],
						"0.75": {
							"pre": [-1.07022, -58.49959, -21.91652],
							"post": [-1.07022, -58.49959, -21.91652],
							"lerp_mode": "catmullrom"
						},
						"1.5": [-1, -56, -22],
						"2.25": {
							"pre": [-1.07022, -58.49959, -21.91652],
							"post": [-1.07022, -58.49959, -21.91652],
							"lerp_mode": "catmullrom"
						},
						"3.0": [-1, -56, -22]
					}
				},
				"arm_right2": {
					"rotation": {
						"0.0": [5.99356, -7.45469, -18.46683],
						"0.75": {
							"pre": [6.03363, -9.94093, -18.73177],
							"post": [6.03363, -9.94093, -18.73177],
							"lerp_mode": "catmullrom"
						},
						"1.5": [5.99356, -7.45469, -18.46683],
						"2.25": {
							"pre": [6.03363, -9.94093, -18.73177],
							"post": [6.03363, -9.94093, -18.73177],
							"lerp_mode": "catmullrom"
						},
						"3.0": [5.99356, -7.45469, -18.46683]
					}
				},
				"arm_right3": {
					"rotation": {
						"0.0": [1.87287, -6.03867, -10.75159],
						"1.5": [1.87287, -6.03867, -10.75159],
						"3.0": [1.87287, -6.03867, -10.75159]
					}
				},
				"hand_right": {
					"rotation": {
						"0.0": [0, 0, -10],
						"1.5": [0, 0, -10],
						"3.0": [0, 0, -10]
					}
				},
				"finger_right1_rotation": {
					"rotation": {
						"0.0": [0, 0, -10],
						"1.5": [0, 0, -10],
						"3.0": [0, 0, -10]
					}
				},
				"finger_right1_2": {
					"rotation": {
						"0.0": [0, 0, -10],
						"1.5": [0, 0, -10],
						"3.0": [0, 0, -10]
					}
				},
				"finger_right2": {
					"rotation": {
						"0.0": [0, 0, -12.5],
						"1.5": [0, 0, -12.5],
						"3.0": [0, 0, -12.5]
					}
				},
				"finger_right3": {
					"rotation": {
						"0.0": [0, 0, -10],
						"1.5": [0, 0, -10],
						"3.0": [0, 0, -10]
					}
				},
				"finger_right4_rotation": {
					"rotation": {
						"0.0": [0, 0, -10],
						"1.5": [0, 0, -10],
						"3.0": [0, 0, -10]
					}
				},
				"finger_right4_2": {
					"rotation": {
						"0.0": [0, 0, -17.5],
						"1.5": [0, 0, -17.5],
						"3.0": [0, 0, -17.5]
					}
				},
				"finger_right5_rotation": {
					"rotation": {
						"0.0": [-7.58967, 36.83503, -12.53061],
						"1.5": [-7.58967, 36.83503, -12.53061],
						"3.0": [-7.58967, 36.83503, -12.53061]
					}
				},
				"finger_right5_2": {
					"rotation": {
						"0.0": [0, 0, -12.5],
						"1.5": [0, 0, -12.5],
						"3.0": [0, 0, -12.5]
					}
				},
				"finger_right2_2": {
					"rotation": {
						"0.0": [0, 0, -12.5],
						"1.5": [0, 0, -12.5],
						"3.0": [0, 0, -12.5]
					}
				},
				"finger_right3_2": {
					"rotation": {
						"0.0": [0, 0, -15],
						"1.5": [0, 0, -15],
						"3.0": [0, 0, -15]
					}
				},
				"arm_left": {
					"rotation": {
						"0.0": [-1, 56, 22],
						"0.75": {
							"pre": [-1.07022, 58.49959, 21.91652],
							"post": [-1.07022, 58.49959, 21.91652],
							"lerp_mode": "catmullrom"
						},
						"1.5": [-1, 56, 22],
						"2.25": {
							"pre": [-1.07022, 58.49959, 21.91652],
							"post": [-1.07022, 58.49959, 21.91652],
							"lerp_mode": "catmullrom"
						},
						"3.0": [-1, 56, 22]
					}
				},
				"arm_left2": {
					"rotation": {
						"0.0": [5.99356, 7.45469, 18.46683],
						"0.75": {
							"pre": [6.03363, 9.94093, 18.73177],
							"post": [6.03363, 9.94093, 18.73177],
							"lerp_mode": "catmullrom"
						},
						"1.5": [5.99356, 7.45469, 18.46683],
						"2.25": {
							"pre": [6.03363, 9.94093, 18.73177],
							"post": [6.03363, 9.94093, 18.73177],
							"lerp_mode": "catmullrom"
						},
						"3.0": [5.99356, 7.45469, 18.46683]
					}
				},
				"arm_left3": {
					"rotation": {
						"0.0": [1.87287, 6.03867, 10.75159],
						"1.5": [1.87287, 6.03867, 10.75159],
						"3.0": [1.87287, 6.03867, 10.75159]
					}
				},
				"hand_left": {
					"rotation": {
						"0.0": [0, 0, 10],
						"1.5": [0, 0, 10],
						"3.0": [0, 0, 10]
					}
				},
				"finger_left1_rotation": {
					"rotation": {
						"0.0": [0, 0, 10],
						"1.5": [0, 0, 10],
						"3.0": [0, 0, 10]
					}
				},
				"finger_left1_2": {
					"rotation": {
						"0.0": [0, 0, 10],
						"1.5": [0, 0, 10],
						"3.0": [0, 0, 10]
					}
				},
				"finger_left2": {
					"rotation": {
						"0.0": [0, 0, 12.5],
						"1.5": [0, 0, 12.5],
						"3.0": [0, 0, 12.5]
					}
				},
				"finger_left2_2": {
					"rotation": {
						"0.0": [0, 0, 12.5],
						"1.5": [0, 0, 12.5],
						"3.0": [0, 0, 12.5]
					}
				},
				"finger_left3": {
					"rotation": {
						"0.0": [0, 0, 10],
						"1.5": [0, 0, 10],
						"3.0": [0, 0, 10]
					}
				},
				"finger_left3_3": {
					"rotation": {
						"0.0": [0, 0, 15],
						"1.5": [0, 0, 15],
						"3.0": [0, 0, 15]
					}
				},
				"finger_left4_rotation": {
					"rotation": {
						"0.0": [0, 0, 10],
						"1.5": [0, 0, 10],
						"3.0": [0, 0, 10]
					}
				},
				"finger_left4_2": {
					"rotation": {
						"0.0": [0, 0, 17.5],
						"1.5": [0, 0, 17.5],
						"3.0": [0, 0, 17.5]
					}
				},
				"finger_left5_rotation": {
					"rotation": {
						"0.0": [-7.58967, -36.83503, 12.53061],
						"1.5": [-7.58967, -36.83503, 12.53061],
						"3.0": [-7.58967, -36.83503, 12.53061]
					}
				},
				"finger_left5_2": {
					"rotation": {
						"0.0": [0, 0, 12.5],
						"1.5": [0, 0, 12.5],
						"3.0": [0, 0, 12.5]
					}
				},
				"tail_right": {
					"scale": {
						"0.0": [0, 0, 0],
						"1.5": [0, 0, 0],
						"3.0": [0, 0, 0]
					}
				},
				"tail_left": {
					"scale": {
						"0.0": [0, 0, 0],
						"1.5": [0, 0, 0],
						"3.0": [0, 0, 0]
					}
				},
				"tail": {
					"rotation": {
						"0.0": [-22.5, 0, 0],
						"1.5": [-22.5, 0, 0],
						"3.0": [-22.5, 0, 0]
					}
				},
				"tail2": {
					"rotation": {
						"0.0": {
							"post": [16.93902, 1.46016, -4.78256],
							"lerp_mode": "catmullrom"
						},
						"1.5": {
							"post": [16.93902, -1.46016, 4.78256],
							"lerp_mode": "catmullrom"
						},
						"3.0": {
							"post": [16.93902, 1.46016, -4.78256],
							"lerp_mode": "catmullrom"
						}
					}
				},
				"tail3": {
					"rotation": {
						"0.0": {
							"post": [23.67575, 4.05012, -9.15075],
							"lerp_mode": "catmullrom"
						},
						"1.5": {
							"post": [23.67575, -4.05012, 9.15075],
							"lerp_mode": "catmullrom"
						},
						"3.0": {
							"post": [23.67575, 4.05012, -9.15075],
							"lerp_mode": "catmullrom"
						}
					}
				},
				"tail4": {
					"rotation": {
						"0.0": {
							"post": [14.65993, 3.21132, -12.08681],
							"lerp_mode": "catmullrom"
						},
						"1.5": {
							"post": [14.65993, -3.21132, 12.08681],
							"lerp_mode": "catmullrom"
						},
						"3.0": {
							"post": [14.65993, 3.21132, -12.08681],
							"lerp_mode": "catmullrom"
						}
					}
				},
				"tail5": {
					"rotation": {
						"0.0": {
							"post": [14.51082, 3.84097, -14.51082],
							"lerp_mode": "catmullrom"
						},
						"1.5": {
							"post": [14.51082, -3.84097, 14.51082],
							"lerp_mode": "catmullrom"
						},
						"3.0": {
							"post": [14.51082, 3.84097, -14.51082],
							"lerp_mode": "catmullrom"
						}
					}
				},
				"tail6": {
					"rotation": {
						"0.0": {
							"post": [14.33501, 4.46375, -16.93839],
							"lerp_mode": "catmullrom"
						},
						"1.5": {
							"post": [14.33501, -4.46375, 16.93839],
							"lerp_mode": "catmullrom"
						},
						"3.0": {
							"post": [14.33501, 4.46375, -16.93839],
							"lerp_mode": "catmullrom"
						}
					}
				},
				"hair2": {
					"rotation": {
						"0.0": [55, 0, 0],
						"0.75": {
							"pre": [57.5, 0, 0],
							"post": [57.5, 0, 0],
							"lerp_mode": "catmullrom"
						},
						"1.5": [55, 0, 0],
						"2.25": {
							"pre": [57.5, 0, 0],
							"post": [57.5, 0, 0],
							"lerp_mode": "catmullrom"
						},
						"3.0": [55, 0, 0]
					}
				},
				"hair3": {
					"rotation": {
						"0.0": [-2.5, 0, 0],
						"0.75": {
							"pre": [0, 0, 0],
							"post": [0, 0, 0],
							"lerp_mode": "catmullrom"
						},
						"1.5": [-2.5, 0, 0],
						"2.25": {
							"pre": [0, 0, 0],
							"post": [0, 0, 0],
							"lerp_mode": "catmullrom"
						},
						"3.0": [-2.5, 0, 0]
					}
				},
				"hair4": {
					"rotation": {
						"0.0": [-12.5, 0, 0],
						"0.75": {
							"pre": [-15, 0, 0],
							"post": [-15, 0, 0],
							"lerp_mode": "catmullrom"
						},
						"1.5": [-12.5, 0, 0],
						"2.25": {
							"pre": [-15, 0, 0],
							"post": [-15, 0, 0],
							"lerp_mode": "catmullrom"
						},
						"3.0": [-12.5, 0, 0]
					}
				},
				"hair5": {
					"rotation": {
						"0.0": [-17.5, 0, 0],
						"0.75": {
							"pre": [-17.5, 0, 0],
							"post": [-17.5, 0, 0],
							"lerp_mode": "catmullrom"
						},
						"1.5": [-17.5, 0, 0],
						"2.25": {
							"pre": [-17.5, 0, 0],
							"post": [-17.5, 0, 0],
							"lerp_mode": "catmullrom"
						},
						"3.0": [-17.5, 0, 0]
					}
				}
			}
		},
		"animation.salaberrant.battle_idle": {
			"loop": true,
			"animation_length": 1.5,
			"bones": {
				"chest": {
					"rotation": {
						"0.0": [0, 0, 0],
						"0.75": {
							"pre": [0, -32.5, 0],
							"post": [0, -32.5, 0],
							"lerp_mode": "catmullrom"
						},
						"1.5": [0, 0, 0]
					}
				}
			}
		},
		"animation.salaberrant.ground_walk": {
			"loop": true
		},
		"animation.salaberrant.sleep": {
			"loop": true
		},
		"animation.salaberrant.faint": {
			"loop": true
		},
		"animation.salaberrant.cry": {
			"loop": true
		},
		"animation.salaberrant.blink": {
			"loop": true
		},
		"animation.salaberrant.recoil": {
			"loop": true
		},
		"animation.salaberrant.physical": {
			"loop": true
		},
		"animation.salaberrant.special": {
			"loop": true
		},
		"animation.salaberrant.status": {
			"loop": true
		},
		"animation.salaberrant.pose": {
			"loop": true,
			"bones": {
				"neck": {
					"rotation": [0.88045, -9.96156, -5.07673]
				},
				"neck2": {
					"rotation": [0, -5, 0]
				},
				"head": {
					"rotation": [-7.5, 0, 0]
				},
				"jaw": {
					"rotation": [25, 0, 0]
				},
				"tongue": {
					"rotation": [2.5, -22.5, 0]
				},
				"tongue2": {
					"rotation": [20, -12.5, 0]
				},
				"tongue3": {
					"rotation": [20, -2.5, 0]
				},
				"leg_right": {
					"rotation": [-1.02015, -5.4453, -49.94916]
				},
				"leg_right2": {
					"rotation": [1.84373, 1.68868, -42.47283]
				},
				"arm_right": {
					"rotation": [-33.30465, -26.65036, 24.88873]
				},
				"arm_right2": {
					"rotation": [-27.32535, -53.65778, 21.30058]
				},
				"arm_right3": {
					"rotation": [-20.77165, -34.68652, 13.18959]
				},
				"hand_right": {
					"rotation": [-34.49013, -8.20574, -9.03336]
				},
				"finger_right1_rotation": {
					"rotation": [8.45862, 5.35355, -29.60382]
				},
				"finger_right1_2": {
					"rotation": [0, 0, -50]
				},
				"finger_right2": {
					"rotation": [1.43455, -7.95233, -27.47436]
				},
				"finger_right3": {
					"rotation": [-6.33586, 5.97845, -34.77733]
				},
				"finger_right4_rotation": {
					"rotation": [0, 0, -5]
				},
				"finger_right4_2": {
					"rotation": [0, 0, -45]
				},
				"finger_right5_2": {
					"rotation": [0, 0, -15]
				},
				"finger_right2_2": {
					"rotation": [0, 0, -22.5]
				},
				"finger_right3_2": {
					"rotation": [0, 0, -25]
				},
				"arm_left": {
					"rotation": [-26.61685, -2.38812, -18.14389]
				},
				"arm_left2": {
					"rotation": [-16.0979, 39.71924, -19.56957]
				},
				"arm_left3": {
					"rotation": [-19.34757, 21.04339, -20.44269]
				},
				"hand_left": {
					"rotation": [-5, 0, 0]
				},
				"finger_left1_rotation": {
					"rotation": [0, 0, 62.5]
				},
				"finger_left1_2": {
					"rotation": [0, 0, 80]
				},
				"finger_left2": {
					"rotation": [0, 0, 70]
				},
				"finger_left2_2": {
					"rotation": [0, 0, 72.5]
				},
				"finger_left3": {
					"rotation": [0, 0, 82.5]
				},
				"finger_left3_3": {
					"rotation": [0, 0, 75]
				},
				"finger_left4_rotation": {
					"rotation": [0, 0, 82.5]
				},
				"finger_left4_2": {
					"rotation": [0, 0, 90]
				},
				"finger_left5_rotation": {
					"rotation": [0, 0, 0]
				},
				"finger_left5_2": {
					"rotation": [0, 0, 2.5]
				},
				"hair2": {
					"rotation": [5, 0, 0]
				},
				"hair3": {
					"rotation": [2.5, 0, 0]
				},
				"hair4": {
					"rotation": [2.5, 0, 0]
				},
				"hair5": {
					"rotation": [2.5, 0, 0]
				}
			}
		}
	}
}